khipu_tools/__init__.py
khipu_tools/_api_mode.py
khipu_tools/_api_requestor.py
khipu_tools/_api_resource.py
khipu_tools/_api_version.py
khipu_tools/_app_info.py
khipu_tools/_banks.py
khipu_tools/_base_address.py
khipu_tools/_client_options.py
khipu_tools/_encode.py
khipu_tools/_error.py
khipu_tools/_error_object.py
khipu_tools/_http_client.py
khipu_tools/_khipu_client.py
khipu_tools/_khipu_object.py
khipu_tools/_khipu_response.py
khipu_tools/_list_object.py
khipu_tools/_listable_api_resource.py
khipu_tools/_payments.py
khipu_tools/_predict.py
khipu_tools/_request_options.py
khipu_tools/_requestor_options.py
khipu_tools/_util.py
khipu_tools/_version.py
khipu_tools-2025.1.0.dist-info/LICENSE.txt
khipu_tools-2025.1.0.dist-info/METADATA
khipu_tools-2025.1.0.dist-info/WHEEL
khipu_tools-2025.1.0.dist-info/RECORD
