Metadata-Version: 2.3
Name: khipu-tools
Version: 2025.1.0
Summary: Set de herramientas para operar con la APIv3 de Khipu
Home-page: http://mariofix.github.io/khipu-tools
License: MIT
Keywords: khipu,pagos,transferencias,payment,subscription,subscripcion
Author: Mario Hernandez
Author-email: mariofix@proton.me
Requires-Python: >=3.9
Classifier: Development Status :: 4 - Beta
Classifier: License :: OSI Approved :: MIT License
Classifier: Programming Language :: Python :: 3.9
Classifier: Programming Language :: Python :: 3.10
Classifier: Programming Language :: Python :: 3.11
Classifier: Programming Language :: Python :: 3.12
Classifier: Intended Audience :: Developers
Classifier: Intended Audience :: Information Technology
Classifier: Topic :: Software Development :: Libraries :: Python Modules
Classifier: Operating System :: OS Independent
Provides-Extra: dev
Requires-Dist: black (>=24.10.0) ; extra == "dev"
Requires-Dist: coverage (>=7.6.9) ; extra == "dev"
Requires-Dist: flask (>=3.1.0) ; extra == "dev"
Requires-Dist: mkdocs-material (>=9.5.49) ; extra == "dev"
Requires-Dist: mkdocstrings[python] (>=0.27.0) ; extra == "dev"
Requires-Dist: mock ; extra == "dev"
Requires-Dist: pre-commit (>=4.0.1) ; extra == "dev"
Requires-Dist: pylint ; extra == "dev"
Requires-Dist: pytest (>=8.3.4) ; extra == "dev"
Requires-Dist: pytest (>=8.3.4) ; extra == "dev"
Requires-Dist: pytest-cov (>=6.0.0) ; extra == "dev"
Requires-Dist: python-dateutil
Requires-Dist: python-slugify (>=8.0.4)
Requires-Dist: requests (>=2.32.3)
Requires-Dist: typing-extensions (>=4.12.2)
Project-URL: Documentation, http://mariofix.github.io/khipu-tools
Project-URL: Repository, http://github.com/mariofix/khipu-tools
